[
  {
    "content": "Add static blog introduction text at top of /blog",
    "status": "in_progress"
  },
  {
    "content": "Create static blog index with H2 titles, dates, excerpts, and links",
    "status": "pending"
  },
  {
    "content": "Ensure each excerpt answers a question first, then introduces story",
    "status": "pending"
  },
  {
    "content": "Add internal links to /tanning in each story",
    "status": "pending"
  },
  {
    "content": "Update StaticFallback for blog page with proper structure",
    "status": "pending"
  },
  {
    "content": "Build and test static blog index",
    "status": "pending"
  }
]