[
  {
    "content": "Update Mary Well AI - Add VIP tanning info (3-month commitment, auto-payment)",
    "status": "completed"
  },
  {
    "content": "Update Tanning page - Emphasize Monthly/VIP value, add VIP pricing to table",
    "status": "completed"
  },
  {
    "content": "Update Laundry page - Add washer sizes, pricing, and laundry machines image",
    "status": "completed"
  },
  {
    "content": "Update Fast Nails booking system - Staff-controlled schedule, prevent double bookings, notifications",
    "status": "in_progress"
  },
  {
    "content": "Test all updates with screenshots",
    "status": "pending"
  }
]